txtoml/__init__.py
txtoml/LICENSE.md
txtoml/txtoml.py
txtoml-1.0.0.dist-info/entry_points.txt
txtoml-1.0.0.dist-info/LICENSE.md
txtoml-1.0.0.dist-info/WHEEL
txtoml-1.0.0.dist-info/METADATA
txtoml-1.0.0.dist-info/RECORD
