Metadata-Version: 2.1
Name: txtoml
Version: 1.0.0
Summary: A command-line utility that allows you to quickly and easily copy dependencies from a Poetry pyproject.toml file to a pip requirements.txt file.
Home-page: https://github.com/jasonalantolbert/txtoml
License: MIT
Keywords: poetry,pyproject,toml,requirements,dependency
Author: Jason Tolbert Jr.
Author-email: jasonalantolbert@gmail.com
Requires-Python: >=3.9.0,<4.0.0
Classifier: License :: OSI Approved :: MIT License
Classifier: Programming Language :: Python :: 3
Classifier: Programming Language :: Python :: 3.9
Requires-Dist: click (>=7.1.2,<8.0.0)
Requires-Dist: toml (>=0.10.2,<0.11.0)
